Metadata-Version: 1.0
Name: sharedlogic
Version: 0.1.0
Summary: Repository for shared functions
Home-page: UNKNOWN
Author: UNKNOWN
Author-email: UNKNOWN
License: UNKNOWN
Platform: UNKNOWN
